wrap_openai/__init__.py
wrap_openai/api_keys.py
wrap_openai/app.py
wrap_openai/cli.py
wrap_openai/models.py
wrap_openai-0.2.1.dist-info/METADATA
wrap_openai-0.2.1.dist-info/WHEEL
wrap_openai-0.2.1.dist-info/entry_points.txt
wrap_openai-0.2.1.dist-info/licenses/LICENSE
wrap_openai-0.2.1.dist-info/RECORD
