Metadata-Version: 2.4
Name: wrap-openai
Version: 0.2.1
Summary: Wrap custom generate function as an OpenAI SDK compatible API service.
Project-URL: Homepage, https://github.com/WKQ9411/wrap-openai
Project-URL: Documentation, https://github.com/WKQ9411/wrap-openai#readme
Project-URL: Repository, https://github.com/WKQ9411/wrap-openai
Project-URL: Issues, https://github.com/WKQ9411/wrap-openai/issues
Author-email: WKQ9411 <wkq9411@gmail.com>
License: MIT
License-File: LICENSE
Keywords: api,chat-completion,fastapi,llm,openai,sdk
Classifier: Development Status :: 4 - Beta
Classifier: Intended Audience :: Developers
Classifier: License :: OSI Approved :: MIT License
Classifier: Programming Language :: Python :: 3
Classifier: Programming Language :: Python :: 3.9
Classifier: Programming Language :: Python :: 3.10
Classifier: Programming Language :: Python :: 3.11
Classifier: Programming Language :: Python :: 3.12
Classifier: Topic :: Internet :: WWW/HTTP :: HTTP Servers
Classifier: Topic :: Software Development :: Libraries :: Python Modules
Requires-Python: >=3.9
Requires-Dist: fastapi>=0.104.0
Requires-Dist: openai>=1.0.0
Requires-Dist: pydantic>=2.0.0
Requires-Dist: requests>=2.31.0
Requires-Dist: uvicorn[standard]>=0.24.0
Provides-Extra: dev
Requires-Dist: black>=23.0.0; extra == 'dev'
Requires-Dist: pytest>=7.0.0; extra == 'dev'
Requires-Dist: ruff>=0.1.0; extra == 'dev'
Provides-Extra: qwen
Requires-Dist: accelerate>=0.24.0; extra == 'qwen'
Requires-Dist: torch>=2.0.0; extra == 'qwen'
Requires-Dist: transformers>=4.35.0; extra == 'qwen'
